[{
    "id": 1,
    "fields": {
        "code": "LUV1",
        "name": "Ludo1",
        "lastname": "Valente1"
    }
},{
    "id": 2,
    "fields": {
        "code": "LUV2",
        "name": "Ludo2",
        "lastname": "Valente2"
    },
    "_fields": {
        "code": "LUV",
        "name": "Ludovic",
        "lastname": "Valente",
        "age": 42,
        "tl": "RBO",
        "xp": 19,
        "skills": "fullstack",
        "clients": "fundsquare",
        "overview": "bla blah blah",
        "plus1": "stronger",
        "plus2": "better",
        "plus3": "faster",
        "plus4": "",
        "minus1": "slow",
        "minus2": "old",
        "minus3": "",
        "minus4": ""
    },
    "objectifs": {
        "past": [{
            "t": "C",
            "text": "Certifciation Azure",
            "desc": "Complete fundamentals Certirication Azure",
            "progress": 80
        }],
        "new": [{
            "t": "C",
            "text": "Certifciation AliCloud",
            "desc": "Complete fundamentals Certirication AliCloud",
            "progress": 0
        }]
    }

}]